README.rst
setup.py
skyhook/__init__.py
skyhook/network.py
skyhook/request.py
skyhook/response.py
skyhook/util.py
skyhook/version.py
skyhook.egg-info/PKG-INFO
skyhook.egg-info/SOURCES.txt
skyhook.egg-info/dependency_links.txt
skyhook.egg-info/requires.txt
skyhook.egg-info/top_level.txt